{
  "created_at": "2022-03-19 11:50:37.486098",
  "stats": {
    "attempts": 0,
    "word_attempts": 0,
    "word_successes": 0,
    "all_correct_count": 0
  },
  "words": {
    "die Wassermelone": "the watermelon",
    "die Limonade": "the lemonade",
    "aufr\u00e4umen": "to tidy up",
    "einverstanden": "agreed",
    "einkaufen": "to shop",
    "drinnen": "indoors",
    "die Einweihungsparty": "the housewarming party",
    "einladen": "to invite",
    "die Vorteile": "the benefits",
    "der Becher": "the mug",
    "sollten": "should",
    "riesig": "huge",
    "der G\u00fcrtel": "the belt",
    "der Dom": "the cathedral",
    "die M\u00f6bel": "the furniture(s)",
    "ungew\u00f6hnlich": "unusual",
    "der Blick": "the view",
    "der Herd": "the stove",
    "weil": "because",
    "wundersch\u00f6n": "lovely",
    "die Krawatte": "the tie",
    "geh\u00f6ren": "to belong to",
    "direkt": "directly",
    "die Quadratmeter": "the square meters",
    "das Kinderzimmer": "the kids' room",
    "gegen\u00fcber": "across from",
    "besonders": "especially",
    "da": "there",
    "der Boden": "the ground",
    "hinausgehen": "to go outside",
    "plaudern": "to chat",
    "wem": "whom",
    "wessen": "whose",
    "wer": "who",
    "die Decke": "the blanket",
    "k\u00fchl": "cool",
    "trotzdem": "nevertheless",
    "auf dem Boden": "on the ground",
    "das Messer": "the knife",
    "die Gabel": "the fork",
    "die So\u00dfe": "the sauce",
    "das W\u00fcrstchen": "the sausage",
    "scharf": "spicy",
    "die W\u00fcrstchen": "the sausages",
    "komisch": "strange"
  }
}